{
  "weapons": [
    {"id": "mech_light_mg", "name": "Лёгкий пулемёт", "slot": "small", "type": "Баллистическое", "damage": "1d8", "attacks": 2, "S": 3, "range": "30/90 м", "heat": 1, "ammo_type": "Лёгкая пулемётная лента", "ammo_capacity": 150, "ammo_per_burst": 15, "price": 350, "rarity": "common", "properties": ["Очередь"]},
    {"id": "mech_heavy_mg", "name": "Тяжёлый пулемёт", "slot": "medium", "type": "Баллистическое", "damage": "1d10", "attacks": 3, "S": 4, "range": "40/120 м", "heat": 2, "ammo_type": "Тяжёлая пулемётная лента", "ammo_capacity": 200, "ammo_per_burst": 25, "price": 600, "rarity": "common", "properties": ["Очередь", "Подавление"]},
    {"id": "mech_mg_nest", "name": "Пулемётное гнездо", "slot": "large", "type": "Баллистическое", "damage": "1d8", "attacks": 5, "S": 4, "range": "30/90 м", "heat": 3, "ammo_type": "Лента для пулемётного гнезда", "ammo_capacity": 300, "ammo_per_burst": 40, "price": 1200, "rarity": "uncommon", "properties": ["Очередь", "Подавление"]},
    {"id": "mech_ac5", "name": "AC/5", "slot": "medium", "type": "Баллистическое", "damage": "2d10", "attacks": 1, "S": 5, "range": "40/120 м", "heat": 1, "ammo_type": "Снаряды AC", "ammo_capacity": 20, "ammo_per_shot": 1, "price": 1000, "rarity": "common", "properties": []},
    {"id": "mech_ac10", "name": "AC/10", "slot": "large", "type": "Баллистическое", "damage": "3d10", "attacks": 1, "S": 6, "range": "30/90 м", "heat": 2, "ammo_type": "Снаряды AC", "ammo_capacity": 15, "ammo_per_shot": 1, "price": 1500, "rarity": "uncommon", "properties": []},
    {"id": "mech_ac20", "name": "AC/20 «Кузнец»", "slot": "large", "type": "Баллистическое", "damage": "4d10", "attacks": 1, "S": 7, "range": "20/60 м", "heat": 3, "ammo_type": "Снаряды AC", "ammo_capacity": 10, "ammo_per_shot": 1, "price": 2500, "rarity": "rare", "properties": ["Крит — отбрасывание"]},
    {"id": "mech_rac5", "name": "RAC/5 «Молот»", "slot": "large", "type": "Баллистическое", "damage": "1d10", "attacks": 3, "S": 5, "range": "30/90 м", "heat": 4, "ammo_type": "Снаряды AC", "ammo_capacity": 15, "ammo_per_burst": 5, "price": 3000, "rarity": "rare", "properties": ["Роторная", "Риск заклинивания (нат. 1)"]},
    {"id": "mech_small_laser", "name": "Малый лазер", "slot": "small", "type": "Энергетическое", "damage": "1d8", "attacks": 1, "S": 4, "range": "15/30 м", "heat": 1, "ammo_type": null, "ammo_capacity": null, "price": 400, "rarity": "common", "properties": ["Игнорирует 1 СУ"]},
    {"id": "mech_medium_laser", "name": "Средний лазер", "slot": "medium", "type": "Энергетическое", "damage": "2d8", "attacks": 1, "S": 5, "range": "30/60 м", "heat": 2, "ammo_type": null, "ammo_capacity": null, "price": 800, "rarity": "common", "properties": ["Игнорирует 1 СУ"]},
    {"id": "mech_large_laser", "name": "Большой лазер", "slot": "large", "type": "Энергетическое", "damage": "3d8", "attacks": 1, "S": 6, "range": "40/80 м", "heat": 4, "ammo_type": null, "ammo_capacity": null, "price": 1800, "rarity": "uncommon", "properties": ["Игнорирует 2 СУ"]},
    {"id": "mech_ppc", "name": "PPC «Луч»", "slot": "large", "type": "Энергетическое", "damage": "3d10", "attacks": 1, "S": 7, "range": "60/120 м", "heat": 5, "ammo_type": null, "ammo_capacity": null, "price": 2500, "rarity": "rare", "properties": ["Игнорирует 2 СУ", "ЭМИ-эффект при крите"]},
    {"id": "mech_pulse_small", "name": "Импульсный лазер (малый)", "slot": "small", "type": "Энергетическое", "damage": "1d6", "attacks": 2, "S": 4, "range": "15/30 м", "heat": 2, "ammo_type": null, "ammo_capacity": null, "price": 700, "rarity": "uncommon", "properties": ["Игнорирует 1 СУ"]},
    {"id": "mech_pulse_medium", "name": "Импульсный лазер (средний)", "slot": "medium", "type": "Энергетическое", "damage": "1d8", "attacks": 3, "S": 5, "range": "20/40 м", "heat": 4, "ammo_type": null, "ammo_capacity": null, "price": 1400, "rarity": "uncommon", "properties": ["Игнорирует 1 СУ"]},
    {"id": "mech_plasma_rifle", "name": "Плазменная винтовка", "slot": "medium", "type": "Энергетическое", "damage": "2d8 огн. + 1d4 кисл.", "attacks": 1, "S": 6, "range": "30/90 м", "heat": 3, "ammo_type": null, "ammo_capacity": null, "price": 1400, "rarity": "rare", "properties": ["Игнорирует 2 СУ", "Зажигает"]},
    {"id": "mech_srm4", "name": "SRM-4", "slot": "medium", "type": "Ракетное", "damage": "1d6", "attacks": 4, "S": 3, "range": "20/60 м", "heat": 2, "ammo_type": "Ракеты SRM", "ammo_capacity": 25, "ammo_per_shot": 4, "price": 1200, "rarity": "common", "properties": ["Залп", "Можно разделять цели"]},
    {"id": "mech_srm6", "name": "SRM-6 «Град»", "slot": "medium", "type": "Ракетное", "damage": "1d6", "attacks": 6, "S": 3, "range": "20/60 м", "heat": 3, "ammo_type": "Ракеты SRM", "ammo_capacity": 15, "ammo_per_shot": 6, "price": 1500, "rarity": "uncommon", "properties": ["Залп", "Можно разделять цели"]},
    {"id": "mech_lrm10", "name": "LRM-10", "slot": "large", "type": "Ракетное", "damage": "1d6", "attacks": 10, "S": 3, "range": "60/200 м", "heat": 4, "ammo_type": "Ракеты LRM", "ammo_capacity": 12, "ammo_per_shot": 10, "price": 2000, "rarity": "uncommon", "properties": ["Залп", "Минимальная дистанция 15 м"]},
    {"id": "mech_lrm15", "name": "LRM-15 «Рой»", "slot": "large", "type": "Ракетное", "damage": "1d6", "attacks": 15, "S": 3, "range": "60/200 м", "heat": 5, "ammo_type": "Ракеты LRM", "ammo_capacity": 8, "ammo_per_shot": 15, "price": 2500, "rarity": "rare", "properties": ["Залп", "Минимальная дистанция 15 м"]},
    {"id": "mech_streaks", "name": "Стрелы (самонаводящиеся)", "slot": "medium", "type": "Ракетное", "damage": "2d6", "attacks": 2, "S": 6, "range": "30/90 м", "heat": 2, "ammo_type": "Стрелы", "ammo_capacity": 12, "ammo_per_shot": 2, "price": 1500, "rarity": "rare", "properties": ["Самонаведение", "Преимущество на попадание"]},
    {"id": "mech_pt_cannon", "name": "ПТ-пушка «Копьё»", "slot": "siege", "type": "Противотанковое", "damage": "4d8", "attacks": 1, "S": 8, "range": "80/200 м", "heat": 3, "ammo_type": "ПТ-снаряды", "ammo_capacity": 5, "ammo_per_shot": 1, "price": 2500, "rarity": "rare", "properties": ["Перезарядка 1 ход"]},
    {"id": "mech_gauss", "name": "Гаусс-пушка", "slot": "siege", "type": "Противотанковое", "damage": "4d10", "attacks": 1, "S": 9, "range": "150/400 м", "heat": 1, "ammo_type": "Гаусс-снаряды", "ammo_capacity": 8, "ammo_per_shot": 1, "price": 6000, "rarity": "legendary", "properties": ["Игнорирует 20 СУ"]},
    {"id": "mech_flamer", "name": "Огнемёт «Горн»", "slot": "medium", "type": "Особое", "damage": "2d6", "attacks": 1, "S": "особый", "range": "Конус 8 м", "heat": 2, "ammo_type": "Топливный бак", "ammo_capacity": 5, "ammo_per_shot": 1, "price": 1200, "rarity": "uncommon", "properties": ["Зажигает", "Игнорирует СУ", "+2 тепла цели"]},
    {"id": "mech_ams", "name": "AMS", "slot": "small", "type": "Защитное", "damage": null, "attacks": null, "S": null, "range": "Реакция", "heat": 0, "ammo_type": "Заряды AMS", "ammo_capacity": 12, "ammo_per_shot": 1, "price": 900, "rarity": "uncommon", "properties": ["Сбивает 1d6 ракет за реакцию"]},
    {"id": "mech_tag", "name": "TAG", "slot": "small", "type": "Специальное", "damage": null, "attacks": null, "S": null, "range": "30 м", "heat": 0, "ammo_type": null, "ammo_capacity": null, "price": 700, "rarity": "uncommon", "properties": ["Подсветка цели", "Преимущество на пробитие ракетами"]},
    {"id": "mech_narc", "name": "NARC", "slot": "small", "type": "Специальное", "damage": null, "attacks": null, "S": null, "range": "20 м", "heat": 1, "ammo_type": "Маячки NARC", "ammo_capacity": 6, "ammo_per_shot": 1, "price": 800, "rarity": "uncommon", "properties": ["Прилипает к цели", "Наводит все ракеты союзников"]},
    {"id": "mech_c3", "name": "C3 Компьютер", "slot": "medium", "type": "Специальное", "damage": null, "attacks": null, "S": null, "range": "100 м", "heat": 0, "ammo_type": null, "ammo_capacity": null, "price": 1500, "rarity": "rare", "properties": ["+1 BS за каждого союзника с C3"]},
    {"id": "mech_smoke", "name": "Дымовая установка", "slot": "small", "type": "Защитное", "damage": null, "attacks": null, "S": null, "range": "Облако 10×10 м", "heat": 1, "ammo_type": "Дымовые заряды", "ammo_capacity": 3, "ammo_per_shot": 1, "price": 200, "rarity": "common", "properties": ["Завеса на 1d4 раунда"]}
  ],
  "ammo_types": {
    "Лёгкая пулемётная лента": {"price": 40, "bursts_per_belt": 10, "variants": {"standard": "—", "ap": "+1 S (+100%)", "tracer": "Преимущество на след. атаку (+50%)", "incendiary": "Поджигает (+80%)"}},
    "Тяжёлая пулемётная лента": {"price": 60, "bursts_per_belt": 8, "variants": {"standard": "—", "ap": "+1 S (+100%)", "tracer": "Преимущество на след. атаку (+50%)", "incendiary": "Поджигает (+80%)"}},
    "Лента для пулемётного гнезда": {"price": 100, "bursts_per_belt": 7, "variants": {"standard": "—", "ap": "+1 S (+100%)", "incendiary": "Поджигает (+80%)"}},
    "Снаряды AC": {"price": 100, "shots_per_ton": 20, "variants": {"standard": "—", "ap": "+1 S (+100%)", "subcaliber": "+2 S, -1d6 урон (+150%)"}},
    "Ракеты SRM": {"price": 100, "per_rocket": true, "variants": {"standard": "S=3, 1d6", "pt": "S=7, 1d8, игнорирует СУ (250 Вт)", "tandem": "S=8, 1d10, игнорирует СУ (350 Вт)", "emi": "Особый (200 Вт)"}},
    "Ракеты LRM": {"price": 100, "per_rocket": true, "variants": {"standard": "S=3, 1d6", "pt": "S=7, 1d8, игнорирует СУ (250 Вт)"}},
    "ПТ-снаряды": {"price": 100, "per_shot": true, "variants": {"standard": "—", "cumulative": "Игнорирует 10 СУ (160 Вт)", "apfsds": "Игнорирует 15 СУ (200 Вт)", "gauss": "Игнорирует 20 СУ (300 Вт)"}},
    "Гаусс-снаряды": {"price": 300, "per_shot": true},
    "Топливный бак": {"price": 40, "shots": 5},
    "Заряды AMS": {"price": 50, "shots": 12},
    "Дымовые заряды": {"price": 30, "shots": 3},
    "Маячки NARC": {"price": 60, "shots": 6},
    "Стрелы": {"price": 150, "per_shot": true}
  }
}